[
  {
    "metadata": {
      "year": 2025,
      "department": "컴퓨터공학과",
      "page_number": 5,
      "table_index": 1,
      "track": "단일전공"
    },
    "table_data_as_string": "[[\"구분\", \"교과목명\", \"과목수\"], [\"전공기초 (12)\", \"선형대수,  미분적분학,  미분방정식,  확률및랜덤변수(EE)\", \"4\"]]"
  },
  {
    "metadata": {
      "year": 2025,
      "department": "컴퓨터공학과",
      "page_number": 6,
      "table_index": 1,
      "track": "단일전공"
    },
    "table_data_as_string": "[[\"구분\", \"교과목명\", \"\", \"과목수\"], [\"전공필수 (42)\", \"객체지향프로그래밍,  웹/파이선프로그래밍(SWCON),  논리회로(EE),  컴퓨터구조,  자료구조,  오픈소스SW개발방법및도구(SWCON),  운영체제,  컴퓨터네트워크,  알고리즘,  데이터베이스,  소프트웨어공학,  기계학습,  캡스톤디자인,  졸업프로젝트,  졸업논문(컴퓨터공학)\", \"\", \"15\"], [\"전공선택 (27)\", \"산학필수(12)\", \"SW스타트업비즈니스,  SW스타트업프로젝트,  빅데이터프로그래밍,  빅데이터프로젝트,  클라우드컴퓨팅,  클라우드프로젝트,  모바일/웹서비스프로그래밍,  모바일/웹서비스프로젝트,  블록체인,  블록체인프로젝트,  최신기술콜로키움1,  최신기술콜로키움2(SWCON),  창업현장실습,  단기현장실습/장기현장실습,  연구연수활동1･2 \", \"16\"], [\"\", \"공통  선택\", \"이산구조,  디자인적사고(SWCON),  신호와시스템(EE),  회로와신호(SWCON),  컴파일러,  프로그래밍언어론,  리눅스시스템프로그래밍,  독립심화학습1･2\", \"9\"], [\"\", \"인공지능/ 빅데이터  분야\", \"빅데이터프로그래밍,  딥러닝,  실전기계학습,  빅데이터프로젝트,  AI네트워킹,  인공지능프로그래밍(AI),  고급딥러닝(AI),  빅데이터마이닝(AI),  자연어처리(SWCON),  강화학습(SWCON)\", \"10\"], [\"\", \"지능형시스템  및  보안  분야\", \"클라우드컴퓨팅,  클라우드프로젝트,  모바일/웹서비스프로그래밍,  모바일/웹서비스프로젝트, 정보보호, 소프트웨어보안, 웹보안, 마이크로서비스프로그래밍(SWCON),  소프트웨어융합보안(SWCON),  풀스택서비스네트워킹(SWCON),  풀스택서비스프로그래밍(SWCON)\", \"11\"], [\"\", \"지능형로봇  및  AIoT  분야\", \"영상처리,  컴퓨터비젼,  AIoT소프트웨어,  AIoT네트워크,  AIoT디지털시스템,  로봇프로그래밍(SWCON),  3D데이터처리(SWCON)\", \"7\"], [\"\", \"메타버스  분야\", \"UI/UX프로그래밍,  메타버스시스템,  컴퓨터그래픽스,  메타버스테이터처리,  인간-컴퓨터상호작용,  가상/증강현실이론및실습(SWCON),  게임인터랙티브테크놀로지(SWCON),  게임프로그래밍입문(SWCON),  게임엔진기초(SWCON),  게임그래픽프로그래밍(SWCON),  인공지능과게임프로그래밍(SWCON),  실감미디어컴퓨팅기초\", \"12\"]]"
  },
  {
    "metadata": {
      "year": 2025,
      "department": "컴퓨터공학과",
      "page_number": 6,
      "table_index": 2,
      "track": "다전공"
    },
    "table_data_as_string": "[[\"구분\", \"교과목명\"], [\"전공기초 (9)\", \"선형대수,  미분적분학,  확률및랜덤변수\"], [\"전공필수 (27)\", \"객체지향프로그래밍,  컴퓨터구조,  자료구조,  운영체제,  컴퓨터네트워크,  알고리즘,  데이터베이스,  소프트웨어공학,  졸업프로젝트,  졸업논문(컴퓨터공학)\"], [\"전공선택 (15)\", \"다전공  전공필수에  포함되지  않은  컴퓨터공학과  단일전공의  전공필수/전공선택  교과목\"]]"
  },
  {
    "metadata": {
      "year": 2025,
      "department": "컴퓨터공학과",
      "page_number": 6,
      "table_index": 3,
      "track": "부전공"
    },
    "table_data_as_string": "[[\"구분\", \"교과목명\", \"\"], [\"부전공과정 \", \"전공필수 (15)\", \"객체지향프로그래밍,  웹/파이선프로그래밍,  자료구조,  운영체제,  알고리즘\"], [\"\", \"전공선택 (6)\", \"부전공과정  전공필수에  포함되지  않은  컴퓨터공학과  단일전공의  전공필수/전공선택  교과목\"]]"
  },
  {
    "metadata": {
      "year": 2025,
      "department": "인공지능학과",
      "page_number": 40,
      "table_index": 1,
      "track": "단일전공"
    },
    "table_data_as_string": "[[\"구분\", \"교과목명\", \"\", \"과목수\"], [\"전공 기초 (12)\", \"선형대수,  미분적분학,  인공지능수학,  확률및랜덤변수(EE)\", \"\", \"4\"], [\"전공 필수 (42)\", \"SW필수  (21)\", \"웹/파이선프로그래밍(SWCON),  객체지향프로그래밍(CSE),  자료구조(CSE),  운영체제(CSE),  알고리즘(CSE),  캡스톤디자인(CSE),  졸업프로젝트(CSE),  졸업논문(인공지능)\", \"8\"], [\"\", \"AI필수 (21)\", \"인공지능개론,  인공지능프로그래밍,  딥러닝(CSE),  실전기계학습(CSE),  기계학습(SWCON),  인공지능과윤리,  고급딥러닝\", \"7\"], [\"전공 선택 (27)\", \"SW선택 (9)\", \"이산구조(CSE),  디자인적사고(SWCON),  데이터베이스(CSE),  컴파일러(CSE),  메타버스시스템(CSE),  소프트웨어공학(CSE),  메타버스테이터처리(CSE),  빅데이터프로그래밍(CSE),  최신기술콜로키움1(CSE),  AI네트워킹(CSE),  모바일/웹서비스프로그래밍(CSE),  마이크로서비스프로그래밍(SWCON),  최신기술콜로키움2(SWCON)\", \"13\"], [\"\", \"AI선택 (18)\", \"UI/UX프로그래밍(CSE),  영상처리(CSE),  컴퓨터그래픽스(CSE),  인간-컴퓨터상호작용(CSE),  컴퓨터비전(CSE),  로봇프로그래밍(SWCON),  자연언어처리(SWCON),  인공지능과게임프로그래밍(SWCON),  강화학습(SWCON),  자연언어학습,  빅데이터마이닝,  정보검색,  지식표현및추론,  통계적학습이론,  설명및신뢰가능한AI, 블록체인(CSE),  AI최신기술,  창업현장실습,  단기현장실습/장기현장실습,  SW스타트업비즈니스(CSE),  SW스타트업프로젝트(CSE),  독립심화학습(인공지능)1,  독립심화학습(인공지능)2,  AI심화학습\", \"25\"]]"
  },
  {
    "metadata": {
      "year": 2025,
      "department": "인공지능학과",
      "page_number": 40,
      "table_index": 2,
      "track": "다전공"
    },
    "table_data_as_string": "[[\"구분\", \"교과목명\", \"\", \"과목수\"], [\"전공 기초 (12)\", \"선형대수,  확률및랜덤변수(EE),  미분적분학,  인공지능수학\", \"\", \"4\"], [\"전공 필수 (30)\", \"SW필수  (12)\", \"자료구조(CSE),  알고리즘(CSE),  캡스톤디자인(CSE),  졸업프로젝트(CSE),  졸업논문(인공지능)\", \"5\"], [\"\", \"AI필수 (18)\", \"인공지능프로그래밍,  기계학습(SWCON),  딥러닝(CSE),  실전기계학습(CSE),  고급딥러닝,  인공지능과윤리\", \"6\"], [\"전공 선택 (18)\", \"SW선택 (3)\", \"이산구조(CSE),  데이터베이스(CSE),  컴파일러(CSE),  메타버스시스템(CSE),  소프트웨어공학(CSE),  메타버스데이터처리(CSE),  빅데이터프로그래밍(CSE),  최신기술콜로키움1(CSE),  AI네트워킹(CSE),  모바일/웹서비스프로그래밍(CSE),  마이크로서비스프로그래밍(SWCON),  최신기술콜로키움2(SWCON)\", \"12\"], [\"\", \"AI선택 (15)\", \"UI/UX프로그래밍(CSE),  영상처리(CSE),  컴퓨터그래픽스(CSE),  인간-컴퓨터상호작용(CSE),  컴퓨터비전(CSE),  로봇프로그래밍(SWCON),  자연언어처리(SWCON),  인공지능과게임프로그래밍(SWCON),  강화학습(SWCON),  자연언어학습,  빅데이터마이닝,  정보검색,  지식표현및추론,  통계적학습이론,  설명및신뢰가능한AI  블록체인(CSE),  AI최신기술,  창업현장실습,  단기현장실습/장기현장실습,  SW스타트업비즈니스(CSE),  SW스타트업프로젝트(CSE),  독립심화학습(인공지능)1,  독립심화학습(인공지능)2,,AI심화학습\", \"25\"]]"
  },
  {
    "metadata": {
      "year": 2025,
      "department": "소프트웨어융합학과",
      "page_number": 68,
      "table_index": 1,
      "track": "단일전공"
    },
    "table_data_as_string": "[[\"구분\", \"교과목명\", \"\", \"\", \"과목수\"], [\"전공 기초 (15)\", \"수학\", \"\", \"미분적분학,  선형대수,  미분방정식,  확률및랜덤변수(EE)\", \"5\"], [\"\", \"물리\", \"\", \"물리학및실험1\", \"\"], [\"전공 필수 (37)\", \"융합필수\", \"\", \"소프트웨어융합개론,  디자인적사고,  최신기술콜로키움1(CSE),  최신기술콜로키움2,  소프트웨어융합캡스톤디자인,  졸업논문(소프트웨어융합)\", \"14\"], [\"\", \"소프트웨어필수\", \"\", \"객체지향프로그래밍(CSE),  웹/파이선프로그래밍,  오픈소스SW개발방법및도구,  자료구조(CSE),  알고리즘(CSE),  운영체제(CSE),  데이터베이스(CSE),  소프트웨어공학(CSE)\", \"\"], [\"전공 선택 (36)\", \"데이터사이언스 트랙\", \"트랙 필수\", \"기계학습,  마이크로서비스프로그래밍,  응용통계학(IE),  데이터사이언스(IE),  응용데이터분석,  데이터분석캡스톤디자인\", \"6\"], [\"\", \"게임콘텐츠 트랙\", \"트랙 필수\", \"게임프로그래밍입문,  게임엔진기초,  게임그래픽프로그래밍,  게임공학,  인공지능과게임프로그래밍,  게임인터랙티브테크놀로지,  게임콘텐츠캡스톤디자인\", \"7\"], [\"\", \"로봇･비전  트랙\", \"트랙 필수\", \"수치해석프로그래밍,  회로와신호,  3D데이터처리,  로봇프로그래밍,  영상분석과패턴인식,  로봇･비전캡스톤디자인\", \"6\"], [\"\", \"융합리더 트랙\", \"\", \"※  전공  선택에서  자유롭게  수강함(최소  12과목–36학점  이상) ※  융합리더트랙에  한하여,  [별표9]의  타전공  교과목의  전공학점(전공선택)을  인정하며, 타전공  교과목의  최대  전공학점  (전공선택)  인정  학점은  본  교육과정의  관련  조항에  준함\", \"0\"], [\"\", \"공통  선택\", \"\", \"가상/증강현실이론및실습,  데이터마이닝(IE),  고급데이터마이닝,  프로세스마이닝,  금융데이터분석,  데이터사이언스및시각화,  자연언어처리,  풀스택서비스네트워킹,  이산구조(CSE),  컴퓨터네트워크(CSE),  리눅스시스템프로그래밍(CSE),  클라우드컴퓨팅(CSE),  SW스타트업비즈니스(CSE),  딥러닝(CSE),  실전기계학습(CSE),  AIoT소프트웨어(CSE),  영상처리(CSE),  모바일/웹서비스프로그래밍(CSE),  정보보호(CSE),  컴퓨터비전(CSE),  빅데이터프로그래밍(CSE),  경영과학1(IE),  경영과학2(IE),  금융공학(IE),  서비스데이터사이언스(IE),  UX디자인(ID),  테크놀로지와디지털콘텐츠(ELC),  세계신화읽기(ELC),  동역학(ME),  메카트로닉스(ME),  자동제어(ME),  시스템동역학(ME),  로봇공학(ME),  로봇제어공학(EE),  독립심화학습1/2,  융합연구1/2/3/4/5/6,  현장실습,  장기현장실습,  강화학습,    풀스택서비스프로그래밍, 디자인프로그래밍, 블록체인(CSE), 데이터분석입문, 소프트웨어융합보안\", \"50\"], [\"\", \"산학필수(10)\", \"\", \"최신기술콜로키움1(CSE),  최신기술콜로키움2,  소프트웨어융합캡스톤디자인,  각  트랙별  캡스톤디자인  과목(데이터분석캡스톤디자인,  게임콘텐츠캡스톤디자인,  로봇･비전캡스톤디자인  중  택1),  현장실습,  장기현장실습\", \"8\"]]"
  },
  {
    "metadata": {
      "year": 2025,
      "department": "소프트웨어융합학과",
      "page_number": 69,
      "table_index": 1,
      "track": "다전공"
    },
    "table_data_as_string": "[[\"구분\", \"교과목명\", \"\", \"\", \"과목수\"], [\"전공 기초 (15)\", \"수학\", \"\", \"미분적분학,  선형대수,  미분방정식,  확률및랜덤변수(EE)\", \"5\"], [\"\", \"물리\", \"\", \"물리학및실험1\", \"\"], [\"전공 필수 (21)\", \"융합필수\", \"\", \"디자인적사고,  소프트웨어융합캡스톤디자인,  졸업논문(소프트웨어융합)\", \"8\"], [\"\", \"소프트웨어필수\", \"\", \"웹/파이선프로그래밍,  오픈소스SW개발방법및도구,  객체지향프로그래밍(CSE),  자료구조(CSE),  알고리즘(CSE)\", \"\"], [\"전공 선택 (24)\", \"데이터사이언스 트랙\", \"트랙 필수\", \"기계학습,  마이크로서비스프로그래밍,  응용통계학(IE),  데이터사이언스(IE),  응용데이터분석,  데이터분석캡스톤디자인\", \"6\"], [\"\", \"게임콘텐츠 트랙\", \"트랙 필수\", \"게임프로그래밍입문,  게임엔진기초,  게임그래픽프로그래밍,  게임공학,  인공지능과게임프로그래밍,  게임콘텐츠캡스톤디자인,  게임인터랙티브테크놀로지\", \"7\"], [\"\", \"로봇･비전  트랙\", \"트랙 필수\", \"수치해석프로그래밍,  회로와신호,  3D데이터처리,  로봇프로그래밍,  영상분석과패턴인식,  로봇･비전캡스톤디자인\", \"6\"], [\"\", \"융합리더  트랙\", \"\", \"※  전공  선택에서  자유롭게  수강함(최소  8과목  –  24학점  이상)\", \"0\"], [\"\", \"공통선택\", \"\", \"가상/증강현실이론및실습,  고급데이터마이닝,  프로세스마이닝,  금융데이터분석,  데이터사이언스및시각화,  자연언어처리,  풀스택서비스네트워킹,  강화학습,  풀스택서비스프로그래밍,  디자인프로그래밍, 단기현장실습(소프트웨어융합학,  데이터분석입문,  소프트웨어융합보안\", \"13\"]]"
  },
  {
    "metadata": {
      "year": 2025,
      "department": "소프트웨어융합학과",
      "page_number": 70,
      "table_index": 1,
      "track": "부전공"
    },
    "table_data_as_string": "[[\"구분\", \"교과목명\", \"과목수\"], [\"전공필수\", \"웹/파이선프로그래밍,  오픈소스SW개발방법및도구,  객체지향프로그래밍(CSE)\", \"3\"], [\"전공선택\", \"기계학습,  마이크로서비스프로그래밍,  데이터사이언스및시각화,  게임프로그래밍입문,  게임엔진기초,  게임그래픽프로그래밍,  게임공학,  가상/증강현실이론및실습,  3D데이터처리,  로봇프로그래밍,  수치해석프로그래밍,  인공지능과게임프로그래밍,  자연언어처리,  풀스택서비스네트워킹,  강화학습,  영상분석과패턴인식,  풀스택서비스프로그래밍,  디자인프로그래밍,  응용데이터분석 \", \"19\"]]"
  },
  {
    "metadata": {
      "year": 2024,
      "department": "컴퓨터공학과",
      "page_number": 8,
      "table_index": 1,
      "track": "단일전공"
    },
    "table_data_as_string": "[[\"구분\", \"교과목명\", \"\", \"과목수\"], [\"전공기초 (15)\", \"선형대수, 미분적분학, 미분방정식, 확률및랜덤변수(EE), 이산구조\", \"\", \"5\"], [\"전공필수 (45)\", \"객체지향프로그래밍, 디자인적사고(SWCON), 웹/파이선프로그래밍(SWCON), 논리회로(EE), 컴퓨터구조, 자료구조, 오픈소스SW개발방법및도구(SWCON), 운영체제, 컴퓨터네트워크, 알고리즘, 데이터베이스, 소프트웨어공학, 기계학습, 캡스톤디자인, 졸업프로젝트, 졸업논문(컴퓨터공학)\", \"\", \"16\"], [\"전공선택 (27)\", \"산학필수(12)\", \"SW스타트업비즈니스, SW스타트업프로젝트, 빅데이터프로그래밍, 빅데이터프로젝트, 클라우드컴퓨팅, 클라우드프로젝트, 모바일/웹서비스프로그래밍, 모바일/웹서비스프로젝트, 블록체인, 최신기술콜로키움1, 최신기술콜로키움2(SWCON), 단기현장실습/장기현장실습, 연구연수활동1･2\", \"15\"], [\"\", \"공통 선택\", \"신호와시스템(EE), 회로와신호(SWCON), 컴파일러, 프로그래밍언어론, 리눅스시스템프로그래밍, 독립심화학습1･2\", \"7\"], [\"\", \"인공지능/ 빅데이터 분야\", \"빅데이터프로그래밍, 딥러닝, 실전기계학습, 빅데이터프로젝트, AI네트워킹, 인공지능프로그래밍(AI), 고급딥러닝(AI), 빅데이터마이닝(AI), 자연어처리(SWCON), 강화학습(SWCON)\", \"10\"], [\"\", \"지능형시스템 및 보안 분야\", \"클라우드컴퓨팅, 클라우드프로젝트, 모바일/웹서비스프로그래밍, 모바일/웹서비스프로젝트, 정보보호, 소프트웨어보안, 웹보안, 마이크로서비스프로그래밍(SWCON), 풀스택서비스네트워킹(SWCON), 풀스택서비스프로그래밍(SWCON)\", \"10\"], [\"\", \"지능형로봇 및 AIoT 분야\", \"영상처리, 컴퓨터비젼, AIoT소프트웨어, AIoT네트워크, AIoT디지털시스템, 로봇프로그래밍(SWCON), 3D데이터처리(SWCON)\", \"7\"], [\"\", \"메타버스 분야\", \"UI/UX프로그래밍, 메타버스시스템, 컴퓨터그래픽스, 메타버스테이터처리, 인간-컴퓨터상호작용, 가상/증강현실이론및실습(SWCON), 게임인터랙티브테크놀로지(SWCON), 게임프로그래밍입문(SWCON,게임엔진기초(SWCON), 게임그래픽프로그래밍(SWCON), 인공지능과게임프로그래밍(SWCON), 실감미디어컴퓨팅기초\", \"12\"]]"
  },
  {
    "metadata": {
      "year": 2024,
      "department": "컴퓨터공학과",
      "page_number": 8,
      "table_index": 2,
      "track": "다전공"
    },
    "table_data_as_string": "[[\"구분\", \"교과목명\"], [\"전공기초(12)\", \"선형대수, 미분적분학, 확률및랜덤변수, 이산구조\"], [\"전공필수(27)\", \"객체지향프로그래밍, 컴퓨터구조, 자료구조, 운영체제, 컴퓨터네트워크, 알고리즘, 데이터베이스, 소프트웨어공학, 졸업프로젝트, 졸업논문(컴퓨터공학)\"], [\"전공선택(15)\", \"다전공 전공필수에 포함되지 않은 컴퓨터공학과 단일전공의 전공필수/전공선택 교과목\"]]"
  },
  {
    "metadata": {
      "year": 2024,
      "department": "컴퓨터공학과",
      "page_number": 8,
      "table_index": 3,
      "track": "부전공"
    },
    "table_data_as_string": "[[\"구분\", \"교과목명\", \"\"], [\"부전공과정\", \"전공필수(15)\", \"객체지향프로그래밍, 웹/파이선프로그래밍, 자료구조, 운영체제, 알고리즘\"], [\"\", \"전공선택(6)\", \"부전공과정 전공필수에 포함되지 않은 컴퓨터공학과 단일전공의 전공필수/전공선택 교과목\"]]"
  },
  {
    "metadata": {
      "year": 2024,
      "department": "인공지능학과",
      "page_number": 40,
      "table_index": 1,
      "track": "단일전공"
    },
    "table_data_as_string": "[[\"구분\", \"교과목명\", \"\", \"과목수\"], [\"전공 기초 (18)\", \"선형대수, 미분적분학, 인공지능개론, 인공지능수학, 확률및랜덤변수(EE), 이산구조(CSE)\", \"\", \"6\"], [\"전공 필수 (42)\", \"SW필수 (24)\", \"디자인적사고(SWCON), 웹/파이선프로그래밍(SWCON), 객체지향프로그래밍(CSE), 자료구조(CSE), 운영체제(CSE), 알고리즘(CSE), 캡스톤디자인, 졸업프로젝트, 졸업논문(인공지능)\", \"9\"], [\"\", \"AI필수 (18)\", \"인공지능프로그래밍, 딥러닝(CSE), 실전기계학습(CSE), 기계학습(SWCON), 인공지능과윤리, 고급딥러닝\", \"6\"], [\"전공 선택 (27)\", \"SW선택 (9)\", \"데이터베이스(CSE), 컴파일러(CSE), 메타버스시스템(CSE), 소프트웨어공학(CSE), 메타버스테이터처리(CSE), 빅데이터프로그래밍(CSE), 최신기술콜로키움1(CSE), AI네트워킹(CSE), 모바일/웹서비스프로그래밍(CSE), 마이크로서비스프로그래밍(SWCON), 최신기술콜로키움2(SWCON)\", \"11\"], [\"\", \"AI선택 (9)\", \"UI/UX프로그래밍(CSE), 영상처리(CSE), 컴퓨터그래픽스(CSE), 인간-컴퓨터상호작용(CSE), 컴퓨터비전(CSE), 로봇프로그래밍(SWCON), 자연언어처리(SWCON),\", \"15\"]]"
  },
  {
    "metadata": {
      "year": 2024,
      "department": "인공지능학과",
      "page_number": 41,
      "table_index": 1,
      "track": "단일전공"
    },
    "table_data_as_string": "[[\"구분\", \"교과목명\", \"\", \"과목수\"], [\"\", \"\", \"인공지능과게임프로그래밍(SWCON), 강화학습(SWCON), 자연언어학습, 빅데이터마이닝, 정보검색, 지식표현및추론, 통계적학습이론, 설명및신뢰가능한AI\", \"\"], [\"전공 선택 (27)\", \"산학트랙 선택 (9)\", \"블록체인(CSE), AI최신기술실전, 단기현장실습/장기현장실습, SW스타트업비즈니스(CSE), SW스타트업프로젝트(CSE)\", \"6\"], [\"\", \"연구트랙 선택 (9)\", \"AI최신기술이론, 독립심화학습(인공지능)1, 독립심화학습(인공지능)2\", \"3\"]]"
  },
  {
    "metadata": {
      "year": 2024,
      "department": "인공지능학과",
      "page_number": 41,
      "table_index": 2,
      "track": "다전공"
    },
    "table_data_as_string": "[[\"구분\", \"교과목명\", \"\", \"과목수\"], [\"전공 기초 (15)\", \"선형대수, 확률및랜덤변수(EE), 미분적분학, 인공지능수학, 이산구조(CSE)\", \"\", \"5\"], [\"전공 필수 (30)\", \"SW필수 (12)\", \"자료구조(CSE), 알고리즘(CSE), 캡스톤디자인, 졸업프로젝트, 졸업논문(인공지능)\", \"5\"], [\"\", \"AI필수 (18)\", \"인공지능프로그래밍, 기계학습(SWCON), 딥러닝(CSE), 실전기계학습(CSE), 고급딥러닝, 인공지능과윤리\", \"6\"], [\"전공 선택 (18)\", \"SW선택 (3)\", \"데이터베이스(CSE), 컴파일러(CSE), 메타버스시스템(CSE), 소프트웨어공학(CSE), 메타버스데이터처리(CSE), 빅데이터프로그래밍(CSE), 최신기술콜로키움1(CSE), AI네트워킹(CSE), 모바일/웹서비스프로그래밍(CSE), 마이크로서비스프로그래밍(SWCON), 최신기술콜로키움2(SWCON)\", \"11\"], [\"\", \"AI선택 (6)\", \"UI/UX프로그래밍(CSE), 영상처리(CSE), 컴퓨터그래픽스(CSE), 인간-컴퓨터상호작용(CSE), 컴퓨터비전(CSE), 로봇프로그래밍(SWCON), 자연언어처리(SWCON), 인공지능과게임프로그래밍(SWCON), 강화학습(SWCON), 자연언어학습, 빅데이터마이닝, 정보검색, 지식표현및추론, 통계적학습이론, 설명및신뢰가능한AI\", \"15\"], [\"\", \"산학트랙 선택 (9)\", \"블록체인(CSE), AI최신기술실전, 단기현장실습/장기현장실습, SW스타트업비즈니스(CSE), SW스타트업프로젝트(CSE)\", \"6\"], [\"\", \"연구트랙 선택 (9)\", \"AI최신기술이론, 독립심화학습(인공지능)1, 독립심화학습(인공지능)2\", \"3\"]]"
  },
  {
    "metadata": {
      "year": 2024,
      "department": "소프트웨어융합학과",
      "page_number": 65,
      "table_index": 1,
      "track": "단일전공"
    },
    "table_data_as_string": "[[\"구분\", \"교과목명\", \"\", \"\", \"과목수\"], [\"전공 기초 (15)\", \"수학\", \"\", \"미분적분학, 선형대수, 미분방정식, 확률및랜덤변수(EE)\", \"5\"], [\"\", \"물리\", \"\", \"물리학및실험1\", \"\"], [\"전공 필수 (37)\", \"융합필수\", \"\", \"소프트웨어융합개론, 디자인적사고, 최신기술콜로키움1(CSE), 최신기술콜로키움2, 소프트웨어융합캡스톤디자인, 졸업논문(소프트웨어융합)\", \"14\"], [\"\", \"소프트웨어필수\", \"\", \"객체지향프로그래밍(CSE), 웹/파이선프로그래밍, 오픈소스SW개발방법및도구, 자료구조(CSE), 알고리즘(CSE), 운영체제(CSE), 데이터베이스(CSE), 소프트웨어공학(CSE)\", \"\"], [\"전공 선택 (36)\", \"데이터사이언스 트랙\", \"트랙 필수\", \"기계학습, 마이크로서비스프로그래밍, 응용통계학(IE), 데이터사이언스(IE), 응용데이터분석, 데이터분석캡스톤디자인\", \"6\"], [\"\", \"게임콘텐츠 트랙\", \"트랙 필수\", \"게임프로그래밍입문, 게임엔진기초, 게임그래픽프로그래밍, 게임공학, 인공지능과게임프로그래밍, 게임인터랙티브테크놀로지, 게임콘텐츠캡스톤디자인\", \"7\"], [\"\", \"로봇･비전 트랙\", \"트랙 필수\", \"수치해석프로그래밍, 회로와신호, 3D데이터처리, 로봇프로그래밍, 영상분석과패턴인식, 로봇･비전캡스톤디자인\", \"6\"], [\"\", \"융합리더 트랙\", \"\", \"※ 전공 선택에서 자유롭게 수강함(최소 12과목–36학점 이상) ※ 융합리더트랙에 한하여, [별표9]의 타전공 교과목의 전공학점(전공선택)을 인정하며, 타전공 교과목의 최대 전공학점 (전공선택) 인정 학점은 본 교육과정의 관련 조항에 준함\", \"0\"], [\"\", \"공통 선택\", \"\", \"가상/증강현실이론및실습, 데이터마이닝(IE), 고급데이터마이닝, 프로세스마이닝, 금융데이터분석, 데이터사이언스및시각화, 자연언어처리, 풀스택서비스네트워킹, 이산구조(CSE), 컴퓨터네트워크(CSE), 리눅스시스템프로그래밍(CSE), 클라우드컴퓨팅(CSE), SW스타트업비즈니스(CSE), 딥러닝(CSE), 실전기계학습(CSE), AIoT소프트웨어(CSE), 영상처리(CSE), 모바일/웹서비스프로그래밍(CSE), 정보보호(CSE), 컴퓨터비전(CSE), 빅데이터프로그래밍(CSE), 경영과학1(IE), 경영과학2(IE), 금융공학(IE), 서비스데이터사이언스(IE), UX디자인(ID), 테크놀로지와디지털콘텐츠(ELC), 세계신화읽기(ELC), 동역학(ME), 메카트로닉스(ME), 자동제어(ME), 시스템동역학(ME), 로봇공학(ME), 로봇제어공학(EE), 독립심화학습1/2, 융합연구1/2/3/4/5/6, 현장실습, 장기현장실습, 강화학습, 풀스택서비스프로그래밍, 디자인프로그래밍, 블록체인(CSE)\", \"48\"], [\"\", \"산학필수(10)\", \"\", \"최신기술콜로키움1(CSE), 최신기술콜로키움2, 소프트웨어융합캡스톤디자인, 각 트랙별 캡스톤디자인 과목(데이터분석캡스톤디자인, 게임콘텐츠캡스톤디자인, 로봇･비전캡스톤디자인 중 택1), 현장실습, 장기현장실습\", \"8\"]]"
  },
  {
    "metadata": {
      "year": 2024,
      "department": "소프트웨어융합학과",
      "page_number": 66,
      "table_index": 1,
      "track": "다전공"
    },
    "table_data_as_string": "[[\"구분\", \"교과목명\", \"\", \"\", \"과목수\"], [\"전공 기초 (15)\", \"수학\", \"\", \"미분적분학, 선형대수, 미분방정식, 확률및랜덤변수(EE)\", \"5\"], [\"\", \"물리\", \"\", \"물리학및실험1\", \"\"], [\"전공 필수 (21)\", \"융합필수\", \"\", \"디자인적사고, 소프트웨어융합캡스톤디자인, 졸업논문(소프트웨어융합)\", \"8\"], [\"\", \"소프트웨어필수\", \"\", \"웹/파이선프로그래밍, 오픈소스SW개발방법및도구, 객체지향프로그래밍(CSE), 자료구조(CSE), 알고리즘(CSE)\", \"\"], [\"전공 선택 (24)\", \"데이터사이언스 트랙\", \"트랙 필수\", \"기계학습, 마이크로서비스프로그래밍, 응용통계학(IE), 데이터사이언스(IE), 응용데이터분석, 데이터분석캡스톤디자인\", \"6\"], [\"\", \"게임콘텐츠 트랙\", \"트랙 필수\", \"게임프로그래밍입문, 게임엔진기초, 게임그래픽프로그래밍, 게임공학, 인공지능과게임프로그래밍, 게임콘텐츠캡스톤디자인, 게임인터랙티브테크놀로지\", \"7\"], [\"\", \"로봇･비전 트랙\", \"트랙 필수\", \"수치해석프로그래밍, 회로와신호, 3D데이터처리, 로봇프로그래밍, 영상분석과패턴인식, 로봇･비전캡스톤디자인\", \"6\"], [\"\", \"융합리더 트랙\", \"\", \"※ 전공 선택에서 자유롭게 수강함(최소 8과목 – 24학점 이상)\", \"0\"], [\"\", \"공통선택\", \"\", \"가상/증강현실이론및실습, 고급데이터마이닝, 프로세스마이닝, 금융데이터분석, 데이터사이언스및시각화, 자연언어처리, 풀스택서비스네트워킹, 강화학습, 풀스택서비스프로그래밍, 디자인프로그래밍, 단기현장실습(소프트웨어융합학)\", \"11\"]]"
  },
  {
    "metadata": {
      "year": 2024,
      "department": "소프트웨어융합학과",
      "page_number": 67,
      "table_index": 1,
      "track": "부전공"
    },
    "table_data_as_string": "[[\"구분\", \"교과목명\", \"과목수\"], [\"전공필수\", \"웹/파이선프로그래밍, 오픈소스SW개발방법및도구, 객체지향프로그래밍(CSE)\", \"3\"], [\"전공선택\", \"기계학습, 마이크로서비스프로그래밍, 데이터사이언스및시각화, 게임프로그래밍입문, 게임엔진기초, 게임그래픽프로그래밍, 게임공학, 가상/증강현실이론및실습, 3D데이터처리, 로봇프로그래밍, 수치해석프로그래밍, 인공지능과게임프로그래밍, 자연언어처리, 풀스택서비스네트워킹, 강화학습, 영상분석과패턴인식, 풀스택서비스프로그래밍, 디자인프로그래밍\", \"18\"]]"
  },
  {
    "metadata": {
      "year": 2023,
      "department": "컴퓨터공학과",
      "page_number": 8,
      "table_index": 1,
      "track": "단일전공"
    },
    "table_data_as_string": "[[\"구분\", \"교과목명\", \"\", \"과목수\"], [\"전공기초 (18)\", \"물리학및실험 1, 선형대수, 미분적분학, 미분방정식, 확률및랜덤변수(EE), 이산구조\", \"\", \"6\"], [\"전공필수 (45)\", \"객체지향프로그래밍, 디자인적사고(SWCON), 웹/파이선프로그래밍(SWCON), 논리회로(EE), 컴퓨터구조, 자료구조, 오픈소스SW개발방법및도구(SWCON), 운영체제, 컴퓨터네트워크, 알고리즘, 데이터베이스, 소프트웨어공학, 기계학습, 캡스톤디자인, 졸업프로젝트, 졸업논문(컴퓨터공학)\", \"\", \"16\"], [\"전공선택 (30)\", \"산학필수(12)\", \"SW스타트업비즈니스, SW스타트업프로젝트, 빅데이터프로그래밍, 빅데이터프로젝트, 클라우드컴퓨팅, 클라우드프로젝트, 모바일/웹서비스프로그래밍, 모바일/웹서비스프로젝트, 최신기술콜로키움 1, 최신기술콜로키움 2(SWCON), 단기현장실습/장기현장실습, 연구연수활동 1･2\", \"14\"], [\"\", \"공통 선택\", \"신호와시스템(EE), 회로와신호(SWCON), 컴파일러, 프로그래밍언어론, 리눅스시스템프로그래밍, 독립심화학습 1･2\", \"7\"], [\"\", \"인공지능/ 빅데이터 분야\", \"빅데이터프로그래밍, 딥러닝, 실전기계학습, 빅데이터프로젝트, AI네트워킹, 인공지능프로그래밍(AI), 고급딥러닝(AI), 빅데이터마이닝(AI) 자연언어처리(SWCON), 강화학습(SWCON)\", \"10\"], [\"\", \"지능형시스템 및 보안 분야\", \"클라우드컴퓨팅, 클라우드프로젝트, 모바일/웹서비스프로그래밍, 모바일/웹서비스프로젝트, 정보보호, 소프트웨어보안, 웹보안, 블록체인, 마이크로서비스프로그래밍(SWCON), 풀스택서비스네트워킹(SWCON), 풀스택서비스프로그래밍(SWCON)\", \"11\"], [\"\", \"지능형로봇 및 AIoT 분야\", \"영상처리, 컴퓨터비젼, AIoT소프트웨어, AIoT네트워크, AIoT디지털시스템, 로봇프로그래밍(SWCON), 3D데이터처리(SWCON)\", \"7\"], [\"\", \"메타버스 분야\", \"UI/UX프로그래밍, 메타버스시스템, 컴퓨터그래픽스, 메타버스테이터처리, 인간-컴퓨터상호작용, 가상/증강현실이론및실습(SWCON), 체감형기술이론및실습(SWCON), 게임프로그래밍입문(SWCON,게임엔진기초(SWCON), 게임그래픽프로그래밍(SWCON), 인공지능과게임프로그래밍(SWCON), 실감미디어컴퓨팅기초\", \"12\"]]"
  },
  {
    "metadata": {
      "year": 2023,
      "department": "컴퓨터공학과",
      "page_number": 8,
      "table_index": 2,
      "track": "다전공"
    },
    "table_data_as_string": "[[\"구분\", \"교과목명\"], [\"전공기초 (12)\", \"선형대수, 미분적분학, 확률및랜덤변수, 이산구조\"], [\"전공필수 (27)\", \"객체지향프로그래밍, 컴퓨터구조, 자료구조, 운영체제, 컴퓨터네트워크, 알고리즘, 데이터베이스, 소프트웨어공학, 졸업프로젝트, 졸업논문(컴퓨터공학)\"], [\"전공선택 (15)\", \"다전공 전공필수에 포함되지 않은 컴퓨터공학과 단일전공의 전공필수/전공선택 교과목\"]]"
  },
  {
    "metadata": {
      "year": 2023,
      "department": "컴퓨터공학과",
      "page_number": 9,
      "table_index": 1,
      "track": "부전공"
    },
    "table_data_as_string": "[[\"구분\", \"교과목명\", \"\"], [\"부전공과정\", \"전공필수 (15)\", \"객체지향프로그래밍, 웹/파이선프로그래밍, 자료구조, 운영체제, 알고리즘\"], [\"\", \"전공선택 (6)\", \"부전공과정 전공필수에 포함되지 않은 컴퓨터공학과 단일전공의 전공필수/전공선택 교과목\"]]"
  },
  {
    "metadata": {
      "year": 2023,
      "department": "인공지능학과",
      "page_number": 39,
      "table_index": 1,
      "track": "단일전공"
    },
    "table_data_as_string": "[[\"구분\", \"교과목명\", \"\", \"과목수\"], [\"전공 기초 (18)\", \"선형대수, 미분적분학, 인공지능개론, 인공지능수학, 확률및랜덤변수(EE), 이산구조(CSE)\", \"\", \"6\"], [\"전공 필수 (42)\", \"SW필수 (24)\", \"디자인적사고(SWCON), 웹/파이선프로그래밍(SWCON), 객체지향프로그래밍(CSE), 자료구조(CSE), 운영체제(CSE), 알고리즘(CSE), 캡스톤디자인, 졸업프로젝트, 졸업논문(인공지능)\", \"9\"], [\"\", \"AI필수 (18)\", \"인공지능프로그래밍, 딥러닝(CSE), 실전기계학습(CSE), 기계학습(SWCON), 인공지능과윤리, 고급딥러닝\", \"6\"], [\"전공 선택 (27)\", \"SW선택 (9)\", \"데이터베이스(CSE), 컴파일러(CSE), 메타버스시스템(CSE), 소프트웨어공학(CSE), 메타버스테이터처리(CSE), 빅데이터프로그래밍(CSE), 최신기술콜로키움 1(CSE), AI네트워킹(CSE), 모바일/웹서비스프로그래밍(CSE), 마이크로서비스프로그래밍(SWCON), 최신기술콜로키움 2(SWCON)\", \"11\"], [\"\", \"AI선택 (9)\", \"UI/UX프로그래밍(CSE), 영상처리(CSE), 컴퓨터그래픽스(CSE), 인간-컴퓨터상호작용(CSE), 컴퓨터비전(CSE), 로봇프로그래밍(SWCON), 자연언어처리(SWCON), 인공지능과게임프로그래밍(SWCON), 강화학습(SWCON), 자연언어학습, 빅데이터마이닝, 정보검색, 지식표현및추론, 통계적학습이론, 설명및신뢰가능한AI\", \"15\"], [\"\", \"산학트랙 선택 (9)\", \"AI최신기술실전, 단기현장실습/장기현장실습, SW스타트업비즈니스(CSE), SW스타트업프로젝트(CSE)\", \"5\"], [\"\", \"연구트랙 선택 (9)\", \"AI최신기술이론, 독립심화학습(인공지능) 1, 독립심화학습(인공지능) 2\", \"3\"]]"
  },
  {
    "metadata": {
      "year": 2023,
      "department": "인공지능학과",
      "page_number": 39,
      "table_index": 2,
      "track": "다전공"
    },
    "table_data_as_string": "[[\"구분\", \"교과목명\", \"\", \"과목수\"], [\"전공 기초 (15)\", \"선형대수, 확률및랜덤변수(EE), 미분적분학, 인공지능수학, 이산구조(CSE)\", \"\", \"5\"], [\"전공 필수 (30)\", \"SW필수 (12)\", \"자료구조(CSE), 알고리즘(CSE), 캡스톤디자인, 졸업프로젝트, 졸업논문(인공지능)\", \"5\"], [\"\", \"AI필수 (18)\", \"인공지능프로그래밍, 기계학습(SWCON), 딥러닝(CSE), 실전기계학습(CSE), 고급딥러닝, 인공지능과윤리\", \"6\"], [\"전공 선택 (18)\", \"SW선택 (3)\", \"데이터베이스(CSE), 컴파일러(CSE), 메타버스시스템(CSE), 소프트웨어공학(CSE), 메타버스데이터처리(CSE), 빅데이터프로그래밍(CSE), 최신기술콜로키움 1(CSE), AI네트워킹(CSE), 모바일/웹서비스프로그래밍(CSE), 마이크로서비스프로그래밍(SWCON), 최신기술콜로키움 2(SWCON)\", \"11\"], [\"\", \"AI선택 (6)\", \"UI/UX프로그래밍(CSE), 영상처리(CSE), 컴퓨터그래픽스(CSE), 인간-컴퓨터상호작용(CSE), 컴퓨터비전(CSE), 로봇프로그래밍(SWCON), 자연언어처리(SWCON), 인공지능과게임프로그래밍(SWCON), 강화학습(SWCON), 자연언어학습, 빅데이터마이닝, 정보검색, 지식표현및추론, 통계적학습이론, 설명및신뢰가능한AI\", \"15\"], [\"\", \"산학트랙 선택 (9)\", \"AI최신기술실전, 단기현장실습/장기현장실습, SW스타트업비즈니스(CSE), SW스타트업프로젝트(CSE)\", \"5\"], [\"\", \"연구트랙 선택 (9)\", \"AI최신기술이론, 독립심화학습(인공지능) 1, 독립심화학습(인공지능) 2\", \"3\"]]"
  },
  {
    "metadata": {
      "year": 2023,
      "department": "소프트웨어융합학과",
      "page_number": 64,
      "table_index": 1,
      "track": "단일전공"
    },
    "table_data_as_string": "[[\"구분\", \"교과목명\", \"\", \"\", \"과목수\"], [\"전공 기초 (15)\", \"수학\", \"\", \"미분적분학, 선형대수, 미분방정식, 확률및랜덤변수(EE)\", \"5\"], [\"\", \"물리\", \"\", \"물리학및실험 1\", \"\"], [\"전공 필수 (37)\", \"융합필수\", \"\", \"소프트웨어융합개론, 디자인적사고, 최신기술콜로키움 1(CSE), 최신기술콜로키움 2, 소프트웨어융합캡스톤디자인, 졸업논문(소프트웨어융합)\", \"14\"], [\"\", \"소프트웨어필수\", \"\", \"객체지향프로그래밍(CSE), 웹/파이선프로그래밍, 오픈소스SW개발방법및도구, 자료구조(CSE), 알고리즘(CSE), 운영체제(CSE), 데이터베이스(CSE), 소프트웨어공학(CSE)\", \"\"], [\"전공 선택 (36)\", \"데이터사이언스 트랙\", \"트랙 필수\", \"기계학습, 마이크로서비스프로그래밍, 응용통계학(IE), 데이터사이언스(IE), 데이터마이닝(IE), 데이터분석캡스톤디자인\", \"6\"], [\"\", \"게임콘텐츠 트랙\", \"트랙 필수\", \"게임프로그래밍입문, 게임엔진기초, 게임그래픽프로그래밍, 게임공학, 인공지능과게임프로그래밍, 가상/증강현실이론및실습, 게임콘텐츠캡스톤디자인\", \"7\"], [\"\", \"로봇･비전 트랙\", \"트랙 필수\", \"회로와신호, 동역학(ME), 3D데이터처리, 로봇프로그래밍, 로봇･비전캡스톤디자인\", \"5\"], [\"\", \"융합리더 트랙\", \"\", \"※ 전공 선택에서 자유롭게 수강함(최소 12과목–36학점 이상) ※ 융합리더트랙에 한하여, [별표9]의 타전공 교과목의 전공학점(전공선택)을 인정하며, 타전공 교과목의 최대 전공학점(전공선택) 인정 학점은 본 교육과정의 관련 조항에 준함\", \"0\"], [\"\", \"공통 선택\", \"\", \"수치해석프로그래밍, 체감형기술이론및실습, 가상/증강현실이론및실습, 고급데이터마이닝, 프로세스마이닝, 금융데이터분석, 데이터사이언스및시각화, 자연언어처리, 풀스택서비스네트워킹, 기초실감미디어프로그래밍, 실감미디어캡스톤디자인, 이산구조(CSE), 컴퓨터네트워크(CSE), 리눅스시스템프로그래밍(CSE), 클라우드컴퓨팅(CSE), 소프트웨어스타트업비즈니스(CSE), 딥러닝(CSE), 실전기계학습(CSE), AIoT소프트웨어(CSE), 영상처리(CSE), 모바일/웹서비스프로그래밍(CSE), 정보보호(CSE), 컴퓨터비전(CSE), 빅데이터프로그래밍(CSE), 경영과학 1(IE), 경영과학 2(IE), 의사결정론(IE), 금융공학(IE), 서비스데이터사이언스(IE), UX 디자인(ID), 테크놀로지와디지털콘텐츠(ELC), 세계신화읽기(ELC), 모션그래픽스(DC), 메카트로닉스(ME), 자동제어(ME), 시스템동역학(ME), 로봇공학(ME), 로봇제어공학(EE), 게임학(DC), 독립심화학습 1/2, 융합연구 1/2/3/4/5/6, 현장실습, 장기현장실습, 강화학습, 영상분석과패턴인식, 풀스택서비스프로그래밍, 디자인프로그래밍\", \"53\"], [\"\", \"산학필수(10)\", \"\", \"최신기술콜로키움 1(CSE), 최신기술콜로키움 2, 소프트웨어융합캡스톤디자인, 각 트랙별 캡스톤디자인 과목(데이터분석캡스톤디자인, 게임콘텐츠캡스톤디자인, 로봇･비전캡스톤디자인 중 택1), 현장실습, 장기현장실습\", \"8\"]]"
  },
  {
    "metadata": {
      "year": 2023,
      "department": "소프트웨어융합학과",
      "page_number": 65,
      "table_index": 1,
      "track": "다전공"
    },
    "table_data_as_string": "[[\"구분\", \"교과목명\", \"\", \"\", \"과목수\"], [\"전공 기초 (15)\", \"수학\", \"\", \"미분적분학, 선형대수, 미분방정식, 확률및랜덤변수(EE)\", \"5\"], [\"\", \"물리\", \"\", \"물리학및실험 1\", \"\"], [\"전공 필수 (21)\", \"융합필수\", \"\", \"디자인적사고, 소프트웨어융합캡스톤디자인, 졸업논문(소프트웨어융합)\", \"8\"], [\"\", \"소프트웨어필수\", \"\", \"웹/파이선프로그래밍, 오픈소스SW개발방법및도구, 객체지향프로그래밍(CSE), 자료구조(CSE), 알고리즘(CSE)\", \"\"], [\"전공 선택 (24)\", \"데이터사이언스 트랙\", \"트랙 필수\", \"기계학습, 마이크로서비스프로그래밍, 응용통계학(IE), 데이터사이언스(IE), 데이터마이닝(IE), 데이터분석캡스톤디자인\", \"6\"], [\"\", \"게임콘텐츠 트랙\", \"트랙 필수\", \"게임프로그래밍입문, 게임엔진기초, 게임그래픽프로그래밍, 게임공학, 인공지능과게임프로그래밍, 가상/증강현실이론및실습, 게임콘텐츠캡스톤디자인\", \"7\"], [\"\", \"로봇･비전 트랙\", \"트랙 필수\", \"회로와신호, 동역학(ME), 3D데이터처리, 로봇프로그래밍, 로봇･비전캡스톤디자인\", \"5\"], [\"\", \"융합리더 트랙\", \"\", \"※ 전공 선택에서 자유롭게 수강함(최소 8과목–24학점 이상)\", \"0\"], [\"\", \"공통선택\", \"\", \"수치해석프로그래밍, 체감형기술이론및실습, 고급데이터마이닝, 프로세스마이닝, 금융데이터분석, 데이터사이언스및시각화, 자연언어처리, 풀스택서비스네트워킹, 기초실감미디어프로그래밍, 게임학(DC), 강화학습, 영상분석과패턴인식, 풀스택서비스프로그래밍, 디자인프로그래밍, 단기현장실습(소프트웨어융합학)\", \"14\"]]"
  },
  {
    "metadata": {
      "year": 2023,
      "department": "소프트웨어융합학과",
      "page_number": 66,
      "table_index": 1,
      "track": "부전공"
    },
    "table_data_as_string": "[[\"구분\", \"교과목명\", \"과목수\"], [\"전공필수\", \"웹/파이선프로그래밍, 오픈소스SW개발방법및도구, 객체지향프로그래밍(CSE)\", \"3\"], [\"전공선택\", \"기계학습, 마이크로서비스프로그래밍, 데이터사이언스및시각화, 게임프로그래밍입문, 게임엔진기초, 게임그래픽프로그래밍, 게임공학, 가상/증강현실이론및실습, 3D데이터처리, 로봇프로그래밍, 수치해석프로그래밍, 인공지능과게임프로그래밍, 자연언어처리, 풀스택서비스네트워킹, 기초실감미디어프로그래밍, 강화학습, 영상분석과패턴인식, 풀스택서비스프로그래밍, 디자인프로그래밍\", \"19\"]]"
  },
  {
    "metadata": {
      "year": 2022,
      "department": "컴퓨터공학과",
      "page_number": 116,
      "table_index": 1,
      "track": "단일전공"
    },
    "table_data_as_string": "[[\"구분\", \"교과목명\", \"\", \"과목수\"], [\"전공기초 (18)\", \"물리학및실험 1, 미분적분학, 선형대수, 확률및랜덤변수(EE), 이산구조, 미분방정식\", \"\", \"6\"], [\"전공필수 (48)\", \"디자인적사고(SWCON), 웹/파이선프로그래밍(SWCON), 객체지향프로그래밍, 논리회로(EE), 컴퓨터구조, 자료구조, 운영체제, 컴퓨터네트워크, 소프트웨어공학, 알고리즘분석, 데이터베이스, 오픈소스SW개발, IT기술영어 1/2/3, 캡스톤디자인 1, 캡스톤디자인 2, 졸업논문(컴퓨터공학), 기계학습\", \"\", \"19\"], [\"전공선택 (30)\", \"산학필수(12)\", \"최신기술프로젝트 1･2, 최신기술콜로키움 1, 최신기술콜로키움 2(SWCON), SW스타트업비즈니스, SW스타트업프로젝트, 연구연수활동 1･2, 단기현장실습/장기현장실습\", \"10\"], [\"\", \"공통 선택\", \"신호와시스템(EE), 문제해결, 형식언어및컴파일러, 파일처리, 멀티미디어시스템, 시스템분석및설계, 프로그래밍언어구조론, 독립심화학습 1･2\", \"8\"], [\"\", \"빅데이터/ 인공지능분야\", \"딥러닝, 실전기계학습, 인공지능, 빅데이터프로그래밍, 클라우드컴퓨팅, 데이터센터프로그래밍(SWCON), AI네트워킹\", \"7\"], [\"\", \"모바일 및 보안 분야\", \"정보보호, 모바일프로그래밍, 웹서비스프로그래밍, 블록체인\", \"4\"], [\"\", \"IoT 분야\", \"리눅스시스템프로그래밍, IoT디지털시스템, IoT소프트웨어, 로봇소프트웨어, IoT네트워크\", \"5\"], [\"\", \"스마트컨텐츠분야\", \"영상처리, 컴퓨터그래픽스, 멀티미디어처리, 인간-컴퓨터상호작용, UI/UX프로그래밍, 컴퓨터비젼\", \"6\"]]"
  },
  {
    "metadata": {
      "year": 2022,
      "department": "컴퓨터공학과",
      "page_number": 116,
      "table_index": 2,
      "track": "다전공"
    },
    "table_data_as_string": "[[\"구분\", \"교과목명\"], [\"전공기초 (12)\", \"미분적분학, 선형대수, 확률및랜덤변수, 이산구조\"], [\"전공필수 (27)\", \"객체지향프로그래밍, 자료구조, 컴퓨터구조, 운영체제, 컴퓨터네트워크, 소프트웨어공학, 알고리즘분석, 데이터베이스, 캡스톤디자인 2, 졸업논문\"], [\"전공선택 (15)\", \"다전공 전공필수에 포함되지 않은 컴퓨터공학과 단일전공의 전공필수/전공선택 교과목\"]]"
  },
  {
    "metadata": {
      "year": 2022,
      "department": "컴퓨터공학과",
      "page_number": 116,
      "table_index": 3,
      "track": "부전공"
    },
    "table_data_as_string": "[[\"구분\", \"교과목명\", \"\"], [\"부전공과정 1\", \"전공필수 (15)\", \"웹/파이선프로그래밍, 객체지향프로그래밍, 자료구조, 운영체제, 알고리즘분석\"], [\"\", \"전공선택 (6)\", \"부전공과정 1 전공필수에 포함되지 않은 컴퓨터공학과 단일전공의 전공필수/전공선택 교과목\"], [\"부전공과정 2 「SW트랙」\", \"전공필수 (24)\", \"웹/파이선프로그래밍, 디자인적사고, 컴퓨터구조, 운영체제, 데이터베이스, 알고리즘분석, 자료구조, 캡스톤디자인 1\"], [\"\", \"전공선택 (6)\", \"웹서비스프로그래밍, 프로그래밍언어구조론\"]]"
  },
  {
    "metadata": {
      "year": 2022,
      "department": "인공지능학과",
      "page_number": 142,
      "table_index": 1,
      "track": "단일전공"
    },
    "table_data_as_string": "[[\"구분\", \"교과목명\", \"\", \"과목수\"], [\"전공 기초 (18)\", \"선형대수, 확률및랜덤변수(EE), 미분적분학, 인공지능개론, 인공지능수학, 이산구조(CSE)\", \"\", \"6\"], [\"전공 필수 (45)\", \"SW필수 (27)\", \"디자인적사고(SWCON), 웹/파이선프로그래밍(SWCON), 객체지향프로그래밍(CSE), 자료구조(CSE), 운영체제(CSE), 알고리즘분석(CSE), 데이터베이스(CSE), 캡스톤디자인 1, 캡스톤디자인 2, 졸업논문\", \"10\"], [\"\", \"AI필수 (18)\", \"인공지능프로그래밍, 기계학습(SWCON), 딥러닝(CSE), 실전기계학습(CSE), 고급딥러닝, 인공지능과윤리\", \"6\"], [\"전공 선택 (27)\", \"SW선택 (9)\", \"형식언어및컴파일러(CSE), 소프트웨어공학(CSE), 모바일프로그래밍(CSE), 웹서비스프로그래밍(CSE), AI네트워킹(CSE), 빅데이터프로그래밍(CSE), 데이터센터프로그래밍(SWCON), 멀티미디어처리(CSE), 멀티미디어시스템(CSE), 최신기술콜로키움 1(CSE), 최신기술콜로키움 2(SWCON)\", \"11\"], [\"\", \"AI선택 (9)\", \"영상처리(CSE), 컴퓨터그래픽스(CSE), 인간-컴퓨터상호작용(CSE), UI/UX프로그래밍(CSE), 컴퓨터비전(CSE), 자연언어처리(SWCON), 자연언어학습, 데이터마이닝, 정보검색, 지식표현및추론, 통계적학습이론, 로봇프로그래밍(SWCON), 인공지능과게임프로그래밍(SWCON), 설명및신뢰가능한AI\", \"14\"], [\"\", \"산학트랙 선택 (9)\", \"최신기술실전, 단기현장실습/장기현장실습, SW스타트업비즈니스(CSE), SW스타트업프로젝트(CSE)\", \"5\"], [\"\", \"연구트랙 선택 (9)\", \"최신기술이론, 독립심화학습(인공지능) 1, 독립심화학습(인공지능) 2\", \"3\"]]"
  },
  {
    "metadata": {
      "year": 2022,
      "department": "인공지능학과",
      "page_number": 142,
      "table_index": 2,
      "track": "다전공"
    },
    "table_data_as_string": "[[\"구분\", \"교과목명\", \"\", \"과목수\"], [\"전공 기초 (15)\", \"선형대수, 확률및랜덤변수(EE), 미분적분학, 인공지능수학, 이산구조(CSE)\", \"\", \"5\"], [\"전공 필수 (33)\", \"SW필수 (15)\", \"자료구조(CSE), 알고리즘분석(CSE), 데이터베이스(CSE), 캡스톤디자인 1, 캡스톤디자인 2, 졸업논문\", \"6\"], [\"\", \"AI필수 (18)\", \"인공지능프로그래밍, 기계학습(SWCON), 딥러닝(CSE), 실전기계학습(CSE), 고급딥러닝, 인공지능과윤리\", \"6\"], [\"전공 선택 (18)\", \"SW선택 (3)\", \"형식언어및컴파일러(CSE), 소프트웨어공학(CSE), 모바일프로그래밍(CSE), 웹서비스프로그래밍(CSE), AI네트워킹(CSE), 빅데이터프로그래밍(CSE), 데이터센터프로그래밍(SWCON), 멀티미디어처리(CSE), 멀티미디어시스템(CSE), 최신기술콜로키움 1(CSE), 최신기술콜로키움 2(SWCON)\", \"11\"], [\"\", \"AI선택 (6)\", \"영상처리(CSE), 컴퓨터그래픽스(CSE), 인간-컴퓨터상호작용(CSE), UI/UX프로그래밍(CSE), 컴퓨터비전(CSE), 자연언어처리(SWCON), 자연언어학습, 데이터마이닝, 정보검색, 지식표현및추론, 통계적학습이론, 로봇프로그래밍(SWCON), 인공지능과게임프로그래밍(SWCON), 설명및신뢰가능한AI\", \"14\"], [\"\", \"산학트랙 선택 (9)\", \"최신기술실전, 단기현장실습/장기현장실습, SW스타트업비즈니스(CSE), SW스타트업프로젝트(CSE)\", \"5\"], [\"\", \"연구트랙 선택 (9)\", \"최신기술이론, 독립심화학습(인공지능) 1, 독립심화학습(인공지능) 2\", \"3\"]]"
  },
  {
    "metadata": {
      "year": 2022,
      "department": "소프트웨어융합학과",
      "page_number": 154,
      "table_index": 1,
      "track": "단일전공"
    },
    "table_data_as_string": "[[\"구분\", \"교과목명\", \"\", \"\", \"과목수\"], [\"전공 기초 (15)\", \"수학\", \"\", \"미분적분학, 선형대수, 미분방정식, 확률및랜덤변수(EE)\", \"5\"], [\"\", \"물리\", \"\", \"물리학및실험 1\", \"\"], [\"전공 필수 (37)\", \"융합필수\", \"\", \"소프트웨어융합개론, 디자인적사고, 최신기술콜로키움 1(CSE), 최신기술콜로키움 2, 소프트웨어융합캡스톤디자인, 졸업논문(소프트웨어융합)\", \"14\"], [\"\", \"소프트웨어필수\", \"\", \"객체지향프로그래밍(CSE), 웹/파이선프로그래밍, 소프트웨어개발방법및도구, 자료구조(CSE), 알고리즘분석(CSE), 운영체제(CSE), 데이터베이스(CSE), 소프트웨어공학(CSE)\", \"\"], [\"전공 선택 (36)\", \"데이터사이언스 트랙\", \"트랙 필수\", \"기계학습, 데이터센터프로그래밍, 응용통계학(IE), 데이터사이언스(IE), 데이터마이닝(IE), 데이터분석캡스톤디자인\", \"6\"], [\"\", \"게임콘텐츠 트랙\", \"트랙 필수\", \"스토리텔링(DC), 게임프로그래밍입문, 게임엔진기초, 게임학(DC), 게임그래픽프로그래밍, 게임공학, 게임콘텐츠캡스톤디자인\", \"7\"], [\"\", \"미래자동차･ 로봇트랙\", \"트랙 필수\", \"회로와신호, 동역학(ME), 로봇센서데이터처리, 로봇프로그래밍, 미래자동차･로봇캡스톤디자인\", \"5\"], [\"\", \"융합리더 트랙\", \"\", \"※ 전공 선택에서 자유롭게 수강함(최소 12과목–36학점 이상) ※ 융합리더트랙에 한하여, [별표9]의 타전공 교과목의 전공학점(전공선택)을 인정하며, 타전공 교과목의 최대 전공학점(전공선택) 인정 학점은 본 교육과정의 관련 조항에 준함\", \"0\"], [\"\", \"공통 선택\", \"\", \"수치해석프로그래밍, 체감형기술이론및실습, 가상/증강현실이론및실습, 고급데이터마이닝, 프로세스마이닝, 금융데이터분석, 데이터사이언스및시각화, 인공지능과게임프로그래밍, 자연언어처리, 풀스택서비스네트워킹, 기초실감미디어프로그래밍, 실감미디어캡스톤디자인, 이산구조(CSE), 컴퓨터네트워크(CSE), 시스템분석및설계(CSE), 리눅스시스템프로그래밍(CSE), 클라우드컴퓨팅(CSE), 소프트웨어스타트업비즈니스(CSE), 딥러닝(CSE), 실전기계학습(CSE), IoT소프트웨어(CSE), 영상처리(CSE), 모바일프로그래밍(CSE), 정보보호(CSE), 컴퓨터비전(CSE), 빅데이터프로그래밍(CSE), 경영과학 1(IE), 경영과학 2(IE), 의사결정론(IE), 금융공학(IE), 서비스데이터사이언스(IE), 3D모델링(DC), 인터랙션디자인(DC), 사운드디자인(DC), 3D애니메이션(DC), 모션그래픽스(DC), 메카트로닉스(ME), 자동제어(ME), 시스템동역학(ME), 로봇공학(ME), 로봇제어공학(EE), 독립심화학습 1/2, 융합연구 1/2/3/4/5/6, 현장실습, 장기현장실습\", \"51\"], [\"\", \"산학필수(10)\", \"\", \"최신기술콜로키움 1(CSE), 최신기술콜로키움 2, 소프트웨어융합캡스톤디자인, 각 트랙별 캡스톤디자인 과목(데이터분석캡스톤디자인, 게임콘텐츠캡스톤디자인, 미래자동차･로봇캡스톤디자인 중 택1), 현장실습, 장기현장실습\", \"8\"]]"
  },
  {
    "metadata": {
      "year": 2022,
      "department": "소프트웨어융합학과",
      "page_number": 155,
      "table_index": 1,
      "track": "다전공"
    },
    "table_data_as_string": "[[\"구분\", \"교과목명\", \"\", \"\", \"과목수\"], [\"전공 기초 (15)\", \"수학\", \"\", \"미분적분학, 선형대수, 미분방정식, 확률및랜덤변수(EE)\", \"5\"], [\"\", \"물리\", \"\", \"물리학및실험 1\", \"\"], [\"전공 필수 (21)\", \"융합필수\", \"\", \"디자인적사고, 소프트웨어융합캡스톤디자인, 졸업논문(소프트웨어융합)\", \"8\"], [\"\", \"소프트웨어필수\", \"\", \"웹/파이선프로그래밍, 소프트웨어개발방법및도구, 객체지향프로그래밍(CSE), 자료구조(CSE), 알고리즘분석(CSE)\", \"\"], [\"전공 선택 (24)\", \"데이터사이언스 트랙\", \"트랙 필수\", \"기계학습, 데이터센터프로그래밍, 응용통계학(IE), 데이터사이언스(IE), 데이터마이닝(IE), 데이터분석캡스톤디자인\", \"6\"], [\"\", \"게임콘텐츠 트랙\", \"트랙 필수\", \"스토리텔링(DC), 게임프로그래밍입문, 게임엔진기초, 게임학(DC), 게임그래픽프로그래밍, 게임공학, 게임콘텐츠캡스톤디자인\", \"7\"], [\"\", \"미래자동차･로봇 트랙\", \"트랙 필수\", \"회로와신호, 동역학(ME), 로봇센서데이터처리, 로봇프로그래밍, 미래자동차･로봇캡스톤디자인\", \"5\"], [\"\", \"융합리더 트랙\", \"\", \"※ 전공 선택에서 자유롭게 수강함(최소 8과목 – 24학점 이상)\", \"0\"], [\"\", \"공통선택\", \"\", \"수치해석프로그래밍, 체감형기술이론및실습, 가상/증강현실이론및실습, 고급데이터마이닝, 프로세스마이닝, 금융데이터분석, 데이터사이언스및시각화, 인공지능과게임프로그래밍, 자연언어처리, 풀스택서비스네트워킹, 기초실감미디어프로그래밍\", \"11\"]]"
  },
  {
    "metadata": {
      "year": 2022,
      "department": "소프트웨어융합학과",
      "page_number": 156,
      "table_index": 1,
      "track": "부전공"
    },
    "table_data_as_string": "[[\"구분\", \"교과목명\", \"과목수\"], [\"전공필수\", \"웹/파이선프로그래밍, 소프트웨어개발방법및도구, 객체지향프로그래밍(CSE)\", \"3\"], [\"전공선택\", \"기계학습, 데이터센터프로그래밍, 데이터사이언스및시각화, 게임프로그래밍입문, 게임엔진기초, 게임그래픽프로그래밍, 게임공학, 가상/증강현실이론및실습, 로봇센서데이터처리, 로봇프로그래밍, 수치해석프로그래밍, 인공지능과게임프로그래밍, 자연언어처리, 풀스택서비스네트워킹, 기초실감미디어프로그래밍\", \"15\"]]"
  },
  {
    "metadata": {
      "year": 2021,
      "department": "컴퓨터공학과",
      "page_number": 8,
      "table_index": 1,
      "track": "단일전공"
    },
    "table_data_as_string": "[[\"구분\", \"교과목명\", \"\", \"과목수\"], [\"전공 기초 (18)\", \"물리학 및 실험 1, 미분적분학, 선형대수, 확률 및 랜덤변수(EE), 이산구조, 미분방정식\", \"\", \"6\"], [\"전공 필수 (48)\", \"디자인적사고(SWCON), 웹/파이선프로그래밍(SWCON), 객체지향프로그래밍, 논리회로(EE), 컴퓨터구조, 자료구조, 운영체제, 컴퓨터네트워크, 소프트웨어공학, 알고리즘분석, 데이터베이스, 오픈소스SW개발, IT기술영어 1/2/3, 캡스톤디자인 1, 캡스톤디자인 2, 졸업논문(컴퓨터공학), 기계학습\", \"\", \"19\"], [\"전공 선택 (30)\", \"산학필수(12)\", \"최신기술프로젝트 1･2, 최신기술콜로키움 1, 최신기술콜로키움 2(SWCON), SW스타트업비즈니스, SW스타트업프로젝트, 연구연수활동 1･2, 단기현장실습/장기현장실습\", \"10\"], [\"\", \"공통 선택\", \"신호와시스템(EE), 문제해결, 형식언어 및 컴파일러, 파일처리, 멀티미디어시스템, 시스템분석 및 설계, 프로그래밍언어구조론, 독립심화학습 1･2\", \"8\"], [\"\", \"빅데이터/ 인공지능분야\", \"딥러닝, 실전기계학습, 인공지능, 빅데이터프로그래밍, 클라우드컴퓨팅, 데이터센터프로그래밍(SWCON), AI 네트워킹\", \"7\"], [\"\", \"모바일 및 보안 분야\", \"정보보호, 모바일프로그래밍, 웹서비스프로그래밍, 블록체인\", \"4\"], [\"\", \"IoT 분야\", \"리눅스시스템프로그래밍, IoT디지털시스템, IoT소프트웨어, 로봇소프트웨어, IoT 네트워크\", \"5\"], [\"\", \"스마트컨텐츠 분야\", \"영상처리, 컴퓨터그래픽스, 멀티미디어처리, 인간-컴퓨터상호작용, UI/UX프로그래밍, 컴퓨터비젼\", \"6\"]]"
  },
  {
    "metadata": {
      "year": 2021,
      "department": "컴퓨터공학과",
      "page_number": 8,
      "table_index": 2,
      "track": "다전공"
    },
    "table_data_as_string": "[[\"구분\", \"교과목명\"], [\"전공기초 (12)\", \"미분적분학, 선형대수, 확률 및 랜덤변수, 이산구조\"], [\"전공필수 (27)\", \"객체지향프로그래밍, 자료구조, 컴퓨터구조, 운영체제, 컴퓨터네트워크, 소프트웨어공학, 알고리즘분석, 데이터베이스, 캡스톤디자인 2, 졸업논문\"], [\"전공선택 (15)\", \"다전공 전공필수에 포함되지 않은 컴퓨터공학과 단일전공의 전공필수/전공선택 교과목\"]]"
  },
  {
    "metadata": {
      "year": 2021,
      "department": "컴퓨터공학과",
      "page_number": 8,
      "table_index": 3,
      "track": "부전공"
    },
    "table_data_as_string": "[[\"구분\", \"교과목명\", \"\"], [\"부전공과정 1\", \"전공필수 (15)\", \"웹/파이선프로그래밍, 객체지향프로그래밍, 자료구조, 운영체제, 알고리즘분석\"], [\"\", \"전공선택 (6)\", \"부전공과정 1 전공필수에 포함되지 않은 컴퓨터공학과 단일전공의 전공필수/전공선택 교과목\"], [\"부전공과정 2 「SW트랙」\", \"전공필수 (24)\", \"웹/파이선프로그래밍, 디자인적사고, 컴퓨터구조, 운영체제, 데이터베이스, 알고리즘분석, 자료구조, 캡스톤디자인 1\"], [\"\", \"전공선택 (6)\", \"웹서비스프로그래밍, 프로그래밍언어구조론\"]]"
  },
  {
    "metadata": {
      "year": 2021,
      "department": "소프트웨어융합학과",
      "page_number": 35,
      "table_index": 1,
      "track": "단일전공"
    },
    "table_data_as_string": "[[\"구분\", \"교과목명\", \"\", \"\", \"과목수\"], [\"전공 기초 (15)\", \"수학\", \"\", \"미분적분학, 선형대수, 미분방정식, 확률 및 랜덤변수(EE)\", \"5\"], [\"\", \"물리\", \"\", \"물리학 및 실험 1\", \"\"], [\"전공 필수 (37)\", \"융합필수\", \"\", \"소프트웨어융합개론, 디자인적사고, 최신기술콜로키움 1(CSE), 최신기술콜로키움 2, 소프트웨어융합캡스톤디자인, 졸업논문(소프트웨어융합)\", \"14\"], [\"\", \"소프트웨어필수\", \"\", \"객체지향프로그래밍(CSE), 웹/파이선프로그래밍, 소프트웨어개발방법 및 도구, 자료구조(CSE), 알고리즘분석(CSE), 운영체제(CSE), 데이터베이스(CSE), 소프트웨어공학(CSE)\", \"\"], [\"전공 선택 (36)\", \"데이터사이언스 트랙\", \"트랙 필수\", \"기계학습, 데이터센터프로그래밍, 응용통계학(IE), 데이터사이언스(IE), 데이터마이닝(IE), 데이터분석캡스톤디자인\", \"6\"], [\"\", \"게임콘텐츠 트랙\", \"트랙 필수\", \"스토리텔링(DC), 게임프로그래밍입문, 게임PX디자인, 게임학(DC), 게임그래픽프로그래밍, 게임공학, 게임콘텐츠캡스톤디자인\", \"7\"], [\"\", \"미래자동차･로봇 트랙\", \"트랙 필수\", \"회로와신호, 동역학(ME), 로봇센서데이터처리, 로봇프로그래밍, 미래자동차･로봇캡스톤디자인\", \"5\"], [\"\", \"융합리더 트랙\", \"\", \"※ 전공 선택에서 자유롭게 수강함 (최소 12과목 – 36학점 이상) ※ 융합리더트랙에 한하여, [별표9]의 타전공 교과목의 전공학점(전공선택)을 인정하며, 타전공 교과목의 최대 전공학점(전공선택) 인정 학점은 본 교육과정의 관련 조항에 준함\", \"0\"], [\"\", \"공통 선택\", \"\", \"수치해석프로그래밍, 체감형기술이론 및 실습, 가상/증강현실이론 및 실습, 고급데이터마이닝, 프로세스마이닝, 금융데이터분석, 데이터사이언스 및 시각화, 게임프로그래밍을통한인공지능과데이터분석, 소프트웨어융합네트워킹, 자연언어처리, 이산구조(CSE), 컴퓨터네트워크(CSE), 시스템분석 및 설계(CSE), 리눅스시스템프로그래밍(CSE), 클라우드컴퓨팅(CSE), 소프트웨어스타트업비즈니스(CSE), 딥러닝(CSE), 실전기계학습(CSE), IoT소프트웨어(CSE), 영상처리(CSE), 모바일프로그래밍(CSE), 정보보호(CSE), 컴퓨터비전(CSE), 빅데이터프로그래밍(CSE), 경영과학 1(IE), 경영과학 2(IE), 의사결정론(IE), 금융공학(IE), 서비스데이터사이언스(IE), 3D모델링(DC), 인터랙션디자인(DC), 사운드디자인(DC), 3D애니메이션(DC), 모션그래픽스(DC), 메카트로닉스(ME), 자동제어(ME), 시스템동역학(ME), 로봇공학(ME), 로봇제어공학(EE), 독립심화학습 1/2, 융합연구 1/2/3/4/5/6, 현장실습, 장기현장실습\", \"49\"], [\"\", \"산학필수(10)\", \"\", \"최신기술콜로키움 1(CSE), 최신기술콜로키움 2, 소프트웨어융합캡스톤디자인, 각 트랙별 캡스톤디자인 과목(데이터분석캡스톤디자인, 게임디자인(DC), 미래자동차･로봇캡스톤디자인 중 택 1), 현장실습, 장기현장실습\", \"8\"]]"
  },
  {
    "metadata": {
      "year": 2021,
      "department": "소프트웨어융합학과",
      "page_number": 36,
      "table_index": 1,
      "track": "다전공"
    },
    "table_data_as_string": "[[\"구분\", \"교과목명\", \"\", \"\", \"과목수\"], [\"전공 기초 (15)\", \"수학\", \"\", \"미분적분학, 선형대수, 미분방정식, 확률 및 랜덤변수(EE)\", \"5\"], [\"\", \"물리\", \"\", \"물리학 및 실험 1\", \"\"], [\"전공 필수 (21)\", \"융합필수\", \"\", \"디자인적사고, 소프트웨어융합캡스톤디자인, 졸업논문(소프트웨어융합)\", \"8\"], [\"\", \"소프트웨어필수\", \"\", \"웹/파이선프로그래밍, 소프트웨어개발방법 및 도구, 객체지향프로그래밍(CSE), 자료구조(CSE), 알고리즘분석(CSE)\", \"\"], [\"전공 선택 (24)\", \"데이터사이언스 트랙\", \"트랙 필수\", \"기계학습, 데이터센터프로그래밍, 응용통계학(IE), 데이터사이언스(IE), 데이터마이닝(IE), 데이터분석캡스톤디자인\", \"6\"], [\"\", \"게임콘텐츠 트랙\", \"트랙 필수\", \"스토리텔링(DC), 게임프로그래밍입문, 게임PX디자인, 게임학(DC), 게임그래픽프로그래밍, 게임공학, 게임콘텐츠캡스톤디자인\", \"7\"], [\"\", \"미래자동차･로봇 트랙\", \"트랙 필수\", \"회로와신호, 동역학(ME), 로봇센서데이터처리, 로봇프로그래밍, 미래자동차･로봇캡스톤디자인\", \"5\"], [\"\", \"융합리더 트랙\", \"\", \"※ 전공 선택에서 자유롭게 수강함(최소 8과목 – 24학점 이상)\", \"0\"], [\"\", \"공통선택\", \"\", \"수치해석프로그래밍, 체감형기술이론 및 실습, 가상/증강현실이론 및 실습, 고급데이터마이닝, 프로세스마이닝, 금융데이터분석, 데이터사이언스 및 시각화, 게임프로그래밍을통한인공지능과데이터분석, 소프트웨어융합네트워킹, 자연언어처리\", \"10\"]]"
  },
  {
    "metadata": {
      "year": 2021,
      "department": "소프트웨어융합학과",
      "page_number": 37,
      "table_index": 1,
      "track": "부전공"
    },
    "table_data_as_string": "[[\"구분\", \"교과목명\", \"과목수\"], [\"전공필수\", \"웹/파이선프로그래밍, 소프트웨어개발방법 및 도구, 객체지향프로그래밍(CSE)\", \"3\"], [\"전공선택\", \"기계학습, 데이터센터프로그래밍, 데이터사이언스 및 시각화, 게임프로그래밍입문, 게임PX디자인, 게임그래픽프로그래밍, 게임공학, 가상/증강현실 이론 및 실습, 로봇센서데이터처리, 로봇프로그래밍, 수치해석프로그래밍, 게임프로그래밍을통한인공지능과데이터분석, 소프트웨어융합네트워킹, 자연언어처리\", \"14\"]]"
  },
  {
    "metadata": {
      "year": 2020,
      "department": "컴퓨터공학과",
      "page_number": 7,
      "table_index": 1,
      "track": "단일전공"
    },
    "table_data_as_string": "[[\"구분\", \"교과목명\", \"과목수\"], [\"전공 기초 (18)\", \"물리학  및  실험  1,  미분적분학,  선형대수,  확률  및  랜덤변수(EE),  이산구조,  미분방정식\", \"6\"]]"
  },
  {
    "metadata": {
      "year": 2020,
      "department": "컴퓨터공학과",
      "page_number": 8,
      "table_index": 1,
      "track": "단일전공"
    },
    "table_data_as_string": "[[\"구분\", \"교과목명\", \"\", \"과목수\"], [\"전공 필수 (45)\", \"디자인적사고(SWCON),  웹/파이선프로그래밍(SWCON),  객체지향프로그래밍,  논리회로(EE),  컴퓨터구조,  자료구조,  운영체제,  컴퓨터네트워크,  소프트웨어공학,  알고리즘분석,  데이터베이스,  오픈소스SW개발,  IT기술영어  1/2/3,  캡스톤디자인  1,  캡스톤디자인  2,  졸업논문(컴퓨터공학)\", \"\", \"18\"], [\"전공 선택 (33)\", \"산학필수(12)\", \"최신기술프로젝트  1･2,  최신기술콜로키움  1,  최신기술콜로키움  2(SWCON),  SW스타트업비즈니스,  SW스타트업프로젝트,  연구연수활동  1･2,  단기현장실습/장기현장실습\", \"10\"], [\"\", \"공통  선택\", \"신호와시스템(EE),  문제해결,  형식언어  및  컴파일러,  파일처리,  멀티미디어시스템,  시스템분석  및  설계,  프로그래밍언어구조론,  독립심화연구  1･2\", \"8\"], [\"\", \"빅데이터/ 인공지능분야\", \"인공지능,  머신러닝,  빅데이터프로그래밍,  클라우드컴퓨팅,  데이터센터프로그래밍(SWCON),  AI  네트워킹\", \"6\"], [\"\", \"모바일  및  보안  분야\", \"정보보호,  모바일프로그래밍,  웹서비스프로그래밍,  블록체인\", \"4\"], [\"\", \"IoT  분야\", \"리눅스시스템프로그래밍,  IoT디지털시스템,  IoT소프트웨어,  로봇소프트웨어,  IoT  네트워크\", \"5\"], [\"\", \"스마트컨텐츠  분야\", \"영상처리,  컴퓨터그래픽스,  멀티미디어처리,  인간-컴퓨터상호작용,  UI/UX프로그래밍,  컴퓨터비젼\", \"6\"]]"
  },
  {
    "metadata": {
      "year": 2020,
      "department": "컴퓨터공학과",
      "page_number": 8,
      "table_index": 2,
      "track": "다전공"
    },
    "table_data_as_string": "[[\"구 분\", \"교과목명\"], [\"전공기초 (12)\", \"미분적분학,  선형대수,  확률  및  랜덤변수,  이산구조\"], [\"전공필수 (27)\", \"객체지향프로그래밍,  자료구조,  컴퓨터구조,  운영체제,  컴퓨터네트워크,  소프트웨어공학,  알고리즘분석,  데이터베이스,  캡스톤디자인  2,  졸업논문\"], [\"전공선택 (15)\", \"다전공  전공필수에  포함되지  않은  컴퓨터공학과  단일전공의  전공필수/전공선택  교과목\"]]"
  },
  {
    "metadata": {
      "year": 2020,
      "department": "컴퓨터공학과",
      "page_number": 8,
      "table_index": 3,
      "track": "부전공"
    },
    "table_data_as_string": "[[\"구 분\", \"교과목명\", \"\"], [\"부전공과정  1 \", \"전공필수 (15)\", \"웹/파이선프로그래밍,  객체지향프로그래밍,  자료구조,  운영체제,  알고리즘분석\"], [\"\", \"전공선택 (6)\", \"부전공과정  1  전공필수에  포함되지  않은  컴퓨터공학과  단일전공의  전공필수/전공선택  교과목\"], [\"부전공과정  2  「소프트웨어과정」\", \"전공필수 (24)\", \"웹/파이선프로그래밍, 디자인적사고, 컴퓨터구조, 운영체제, 데이터베이스, 알고리즘분석, 자료구조, 캡스톤디자인 1\"], [\"\", \"전공선택 (6)\", \"웹서비스프로그래밍,  프로그래밍언어구조론\"]]"
  },
  {
    "metadata": {
      "year": 2020,
      "department": "소프트웨어융합학과",
      "page_number": 34,
      "table_index": 1,
      "track": "단일전공"
    },
    "table_data_as_string": "[[\"구분\", \"교과목명\", \"\", \"\", \"과목수\"], [\"전공 기초 (15)\", \"수학\", \"\", \"미분적분학,  선형대수,  미분방정식,  확률  및  랜덤변수(EE)\", \"5\"], [\"\", \"물리\", \"\", \"물리학  및  실험  1\", \"\"], [\"전공 필수 (37)\", \"융합필수\", \"\", \"소프트웨어융합개론,  디자인적사고,  최신기술콜로키움  1(CSE),  최신기술콜로키움  2,  소프트웨어융합캡스톤디자인,  졸업논문(소프트웨어융합)\", \"14\"], [\"\", \"소프트웨어필수\", \"\", \"객체지향프로그래밍(CSE),  웹/파이선프로그래밍,  소프트웨어개발방법  및  도구,  자료구조(CSE),  알고리즘분석(CSE),  운영체제(CSE),  데이터베이스(CSE),  소프트웨어공학(CSE)\", \"\"], [\"전공 선택 (36)\", \"데이터사이언스 트랙\", \"트랙 필수\", \"응용통계학(IE),  데이터센터프로그래밍,  데이터사이언스(IE),  데이터마이닝(IE),  데이터분석캡스톤디자인\", \"14\"], [\"\", \"\", \"트랙 선택\", \"경영과학  1(IE),  경영과학  2(IE),  의사결정론(IE),  고급데이터마이닝,  금융공학(IE),  프로세스마이닝,  서비스데이터사이언스(IE),  금융데이터분석,  데이터사이언스  및  시각화,  머신러닝(CSE)\", \"\"], [\"\", \"게임콘텐츠 트랙\", \"트랙 필수\", \"스토리텔링(DC),  게임프로그래밍입문,  게임PX디자인,  게임학(DC),  게임그래픽프로그래밍,  게임공학,  게임디자인(DC)\", \"14\"], [\"\", \"\", \"트랙 선택\", \"3D모델링(DC),  인터랙션디자인(DC),  사운드디자인(DC),  3D애니메이션(DC),  체감형기술  이론  및  실습,  가상/증강현실이론  및  실습,  모션그래픽스(DC)\", \"\"], [\"\", \"미래자동차･로봇 트랙\", \"트랙 필수\", \"물리학  및  실험  2(APHY),  동역학(ME),  전기전자회로(ME),  신호와시스템(EE),  미래자동차･로봇프로그래밍,  메카트로닉스(ME)\", \"17\"], [\"\", \"\", \"트랙 선택\", \"계측공학(ME),  자동제어(ME),  혁신적미래자동차로봇디자인,  시스템동역학(ME),  미래자동차･로봇캡스톤디자인,  로봇제어공학(EE),  로봇공학(ME),  IoT소프트웨어(CSE),  영상처리(CSE),  디지털신호처리(EE),  디지털통신(EE)\", \"\"], [\"\", \"융합리더 트랙\", \"\", \"※  전공  선택에서  자유롭게  수강함  (최소  12과목  ­  36학점  이상) ※  융합리더트랙에  한하여,  [별표9]의  타전공  교과목의  전공학점(전공선택)을  인정하며, 타전공  교과목의  최대  전공학점(전공선택)  인정  학점은  본  교육과정의  관련  조항에  준함\", \"0\"], [\"\", \"공통  선택\", \"\", \"게임프로그래밍을통한인공지능과데이터분석,  소프트웨어융합네트워킹,  수치해석프로그래밍, 이산구조(CSE),  시스템분석  및  설계(CSE),  컴퓨터그래픽스(CSE),  컴퓨터네트워크(CSE),  SW스타트업비지니스(CSE),  모바일프로그래밍(CSE),  인공지능(CSE),  정보보호(CSE) 독립심화학습  1/2,  융합연구  1/2/3/4/5/6,  현장실습,  장기현장실습,  컴퓨터비전(CSE),  리눅스시스템프로그래밍(CSE),  클라우드컴퓨팅(CSE),  빅데이터프로그래밍(CSE)\", \"25\"], [\"\", \"산학필수(10)\", \"\", \"최신기술콜로키움  1(CSE),  최신기술콜로키움  2,  소프트웨어융합캡스톤디자인,  각  트랙별  캡스톤디자인  과목  (데이터분석캡스톤디자인,  게임디자인(DC),  미래자동차･로봇캡스톤디자인  중  택  1),  현장실습,  장기현장실습\", \"8\"]]"
  },
  {
    "metadata": {
      "year": 2020,
      "department": "소프트웨어융합학과",
      "page_number": 35,
      "table_index": 1,
      "track": "다전공"
    },
    "table_data_as_string": "[[\"구분\", \"교과목명\", \"\", \"\", \"과목수\"], [\"전공 기초 (15)\", \"수학\", \"\", \"미분적분학,  선형대수,  미분방정식,  확률  및  랜덤변수(EE)\", \"5\"], [\"\", \"물리\", \"\", \"물리학  및  실험  1\", \"\"], [\"전공 필수 (21)\", \"융합필수\", \"\", \"디자인적사고,  소프트웨어융합캡스톤디자인,  졸업논문(소프트웨어융합)\", \"8\"], [\"\", \"소프트웨어필수\", \"\", \"객체지향프로그래밍(CSE),  웹/파이선프로그래밍,  소프트웨어개발방법  및  도구,  자료구조(CSE),  알고리즘분석(CSE)\", \"\"], [\"전공 선택 (24)\", \"데이터사이언스 트랙\", \"트랙 필수\", \"응용통계학(IE),  데이터센터프로그래밍,  데이터사이언스(IE),  데이터마이닝(IE),  데이터분석캡스톤디자인\", \"14\"], [\"\", \"\", \"트랙 선택\", \"경영과학  1(IE),  경영과학  2(IE),  의사결정론(IE),  고급데이터마이닝,  금융공학(IE),  프로세스마이닝,  서비스데이터사이언스(IE),  금융데이터분석,  데이터사이언스  및  시각화,  머신러닝(CSE)\", \"\"], [\"\", \"게임콘텐츠 트랙\", \"트랙 필수\", \"스토리텔링(DC),  게임프로그래밍입문,  게임PX디자인,  게임학(DC),  게임그래픽프로그래밍,  게임공학,  게임디자인(DC)\", \"14\"], [\"\", \"\", \"트랙 선택\", \"3D모델링(DC),  인터랙션디자인(DC),  사운드디자인(DC),  3D애니메이션(DC),  체감형기술이론  및  실습,  가상/증강현실이론  및  실습,  모션그래픽스(DC)\", \"\"], [\"\", \"미래자동차･로봇 트랙\", \"트랙 필수\", \"물리학  및  실험  2(APHY),  동역학(ME),  전기전자회로(ME),  신호와시스템(EE),  미래자동차･로봇프로그래밍,  메카트로닉스(ME)\", \"17\"], [\"\", \"\", \"트랙 선택\", \"계측공학(ME),  자동제어(ME),  혁신적미래자동차로봇디자인,  시스템동역학(ME),  미래자동차･로봇  캡스톤디자인,  로봇제어공학(EE),  로봇공학(ME),  IoT소프트웨어(CSE),  영상처리(CSE),  디지털신호처리(EE),  디지털통신(EE)\", \"\"], [\"\", \"융합리더  트랙\", \"\", \"※  전공  선택에서  자유롭게  수강함  (최소  8과목  ­  24학점  이상)\", \"0\"], [\"\", \"공통선택\", \"\", \"게임프로그래밍을통한인공지능과데이터분석,  소프트웨어융합네트워킹,  수치해석프로그래밍\", \"3\"]]"
  },
  {
    "metadata": {
      "year": 2020,
      "department": "소프트웨어융합학과",
      "page_number": 36,
      "table_index": 1,
      "track": "부전공"
    },
    "table_data_as_string": "[[\"부전공 유형\", \"심화형\", \"인증형\", \"창업형\", \"실현형\"], [\"\", \"부전공(심화형)\", \"부전공(인증형/창업형/실현형)\", \"\", \"\"], [\"전공 필수\", \"객체지향프로그래밍(CSE),  웹/파이선프로그래밍, 디자인적사고,  소프트웨어개발방법  및  도구,  자료구조(CSE),  알고리즘분석(CSE)\", \"객체지향프로그래밍(CSE),    자료구조(CSE),  알고리즘분석(CSE), 운영체제(CSE)\", \"객체지향프로그래밍(CSE),  웹/파이선프로그래밍, 디자인적사고,  소프트웨어개발방법 및 도구\", \"객체지향프로그래밍(CSE),  웹/파이선프로그래밍, 디자인적사고,  소프트웨어개발방법  및  도구\"], [\"\", \"6과목 (18학점  이수)\", \"4과목 (12학점  이수)\", \"4과목 (12학점  이수)\", \"4과목 (12학점  이수)\"], [\"전공 선택\", \"※  [표2]의  전공선택  과목  중  12학점  이상  이수\", \"이산구조(CSE),  데이터베이스(CSE),  소프트웨어공학(CSE), 컴퓨터네트워크(CSE), 모바일프로그래밍(CSE)\", \"데이터센터프로그래밍,  SW스타트업비지니스(CSE), 융합연구  1,2,3,4,5,6  (융합연구에서는  3학점만  가능) \", \"※  [표1]의  전공선택  과목  중  9학점  이상  이수\"], [\"\", \"- (12학점  이수)\", \"5과목 (9학점  이수)\", \"8과목 (9학점  이수)\", \"- (9학점  이수)\"]]"
  }
]